{"namespace":"MizanTalalLawDesignSystem_c3bb63","components":[{"name":"Button","sourcePath":"components/actions/Button.jsx"},{"name":"IconButton","sourcePath":"components/actions/IconButton.jsx"},{"name":"MessageBubble","sourcePath":"components/chat/MessageBubble.jsx"},{"name":"Avatar","sourcePath":"components/data/Avatar.jsx"},{"name":"Badge","sourcePath":"components/data/Badge.jsx"},{"name":"Card","sourcePath":"components/data/Card.jsx"},{"name":"Citation","sourcePath":"components/data/Citation.jsx"},{"name":"Alert","sourcePath":"components/feedback/Alert.jsx"},{"name":"Checkbox","sourcePath":"components/forms/Checkbox.jsx"},{"name":"Input","sourcePath":"components/forms/Input.jsx"},{"name":"Select","sourcePath":"components/forms/Select.jsx"},{"name":"Switch","sourcePath":"components/forms/Switch.jsx"},{"name":"Textarea","sourcePath":"components/forms/Textarea.jsx"},{"name":"Tabs","sourcePath":"components/navigation/Tabs.jsx"}],"startingPoints":[{"name":"legal-assistant","path":"ui_kits/legal-assistant/index.html","previewPath":"ui_kits/legal-assistant/index.html","kind":"screen","section":"Legal Assistant","subtitle":"Mizan legal-assistant chat app — sidebar, composer, cited answers","viewport":"1280x800"}],"cards":[{"path":"guidelines/brand-logo-navy.html","group":"Brand","viewport":"700x180","subtitle":"Reversed lockup for dark surfaces","name":"الشعار على الكحلي · Logo on navy"},{"path":"guidelines/brand-logo.html","group":"Brand","viewport":"700x180","subtitle":"Mizan mark + Arabic wordmark, primary on ivory","name":"الشعار · Logo lockup"},{"path":"guidelines/brand-pairings.html","group":"Brand","viewport":"700x160","subtitle":"Approved navy / gold / ivory combinations","name":"الإقتران اللوني · Pairings"},{"path":"guidelines/color-brand.html","group":"Colors","viewport":"700x150","subtitle":"Navy authority + gold justice — the two core brand colors","name":"ألوان الهوية · Brand"},{"path":"guidelines/color-gold.html","group":"Colors","viewport":"700x130","subtitle":"50 → 900 — accents, emphasis, and the justice motif","name":"تدرّج الذهبي · Gold scale"},{"path":"guidelines/color-navy.html","group":"Colors","viewport":"700x130","subtitle":"50 → 950 — surfaces, text, and inverse backgrounds","name":"تدرّج الكحلي · Navy scale"},{"path":"guidelines/color-neutrals.html","group":"Colors","viewport":"700x140","subtitle":"Warm paper surfaces and ink text values","name":"محايدات دافئة · Neutrals"},{"path":"guidelines/color-status.html","group":"Colors","viewport":"700x130","subtitle":"Success, warning, danger, info — solid + soft pairs","name":"حالات دلالية · Status"},{"path":"components/actions/buttons.card.html","group":"Components","viewport":"700x230","subtitle":"Variants, sizes, icons, and states","name":"الأزرار · Buttons"},{"path":"components/chat/chat.card.html","group":"Components","viewport":"700x260","subtitle":"User & assistant message bubbles with citations","name":"فقاعات المحادثة · Chat"},{"path":"components/data/data.card.html","group":"Components","viewport":"700x300","subtitle":"Badge, Avatar, Card, and the legal Citation","name":"عرض البيانات · Data Display"},{"path":"components/feedback/feedback.card.html","group":"Components","viewport":"700x240","subtitle":"Alert banners and the Tabs bar","name":"التنبيهات والتبويب · Feedback & Nav"},{"path":"components/forms/forms.card.html","group":"Components","viewport":"700x340","subtitle":"Input, Textarea, Select, Checkbox, Switch","name":"حقول الإدخال · Forms"},{"path":"components/navigation/tabs.card.html","group":"Components","viewport":"700x160","subtitle":"Underline tab bar with gold indicator and counts","name":"التبويب · Tabs"},{"path":"ui_kits/legal-assistant/index.html","group":"Legal Assistant","viewport":"1280x800","subtitle":"Full chat product — login, suggestions, threaded answers with citations","name":"المساعد القانوني · App"},{"path":"guidelines/spacing-radius.html","group":"Spacing","viewport":"700x150","subtitle":"xs 3 · sm 5 · md 8 · lg 12 · xl 16 · pill","name":"الزوايا · Radius"},{"path":"guidelines/spacing-scale.html","group":"Spacing","viewport":"700x150","subtitle":"4px base grid — space-1 (4) → space-10 (64)","name":"مقياس المسافات · Spacing"},{"path":"guidelines/spacing-shadows.html","group":"Spacing","viewport":"700x170","subtitle":"Navy-tinted soft shadows — xs → xl","name":"الظلال · Elevation"},{"path":"guidelines/type-body.html","group":"Type","viewport":"700x220","subtitle":"Body 16/1.6 · small 14 · eyebrow caps · link","name":"المتن والتسميات · Body & Labels"},{"path":"guidelines/type-headings.html","group":"Type","viewport":"700x230","subtitle":"IBM Plex Sans Arabic — display 56 / h1 40 / h2 32 / h3 25","name":"العناوين · Display & Headings"},{"path":"guidelines/type-mono.html","group":"Type","viewport":"700x160","subtitle":"IBM Plex Mono — case numbers, dates, amounts (tabular)","name":"الأرقام · Mono figures"},{"path":"guidelines/type-weights.html","group":"Type","viewport":"700x130","subtitle":"Light 300 · Regular 400 · Medium 500 · Semibold 600 · Bold 700","name":"الأوزان · Weights"}],"templates":[],"hasThumbnailHtml":false,"globalCssPaths":["tokens/fonts.css","tokens/colors.css","tokens/typography.css","tokens/spacing.css","tokens/radius.css","tokens/shadows.css","tokens/motion.css","tokens/base.css","styles.css"],"tokens":[{"name":"--navy-50","value":"#F2F6FA","kind":"color","definedIn":"tokens/colors.css"},{"name":"--navy-100","value":"#E2EBF3","kind":"color","definedIn":"tokens/colors.css"},{"name":"--navy-200","value":"#C2D3E5","kind":"color","definedIn":"tokens/colors.css"},{"name":"--navy-300","value":"#93B0CE","kind":"color","definedIn":"tokens/colors.css"},{"name":"--navy-400","value":"#5B83AE","kind":"color","definedIn":"tokens/colors.css"},{"name":"--navy-500","value":"#2E5C8C","kind":"color","definedIn":"tokens/colors.css"},{"name":"--navy-600","value":"#1E4670","kind":"color","definedIn":"tokens/colors.css"},{"name":"--navy-700","value":"#163A63","kind":"color","definedIn":"tokens/colors.css"},{"name":"--navy-800","value":"#0F2A4A","kind":"color","definedIn":"tokens/colors.css"},{"name":"--navy-900","value":"#0A1C32","kind":"color","definedIn":"tokens/colors.css"},{"name":"--navy-950","value":"#061325","kind":"color","definedIn":"tokens/colors.css"},{"name":"--gold-50","value":"#FBF8F1","kind":"color","definedIn":"tokens/colors.css"},{"name":"--gold-100","value":"#F5EEDF","kind":"color","definedIn":"tokens/colors.css"},{"name":"--gold-200","value":"#ECDDC0","kind":"color","definedIn":"tokens/colors.css"},{"name":"--gold-300","value":"#E0CAA0","kind":"color","definedIn":"tokens/colors.css"},{"name":"--gold-400","value":"#D0B27B","kind":"color","definedIn":"tokens/colors.css"},{"name":"--gold-500","value":"#C19E5E","kind":"color","definedIn":"tokens/colors.css"},{"name":"--gold-600","value":"#B8924C","kind":"color","definedIn":"tokens/colors.css"},{"name":"--gold-700","value":"#9C7A3C","kind":"color","definedIn":"tokens/colors.css"},{"name":"--gold-800","value":"#7C6130","kind":"color","definedIn":"tokens/colors.css"},{"name":"--gold-900","value":"#5E4926","kind":"color","definedIn":"tokens/colors.css"},{"name":"--ivory","value":"#F7F5F0","kind":"color","definedIn":"tokens/colors.css"},{"name":"--paper","value":"#FBFAF6","kind":"color","definedIn":"tokens/colors.css"},{"name":"--paper-2","value":"#F1EEE6","kind":"color","definedIn":"tokens/colors.css"},{"name":"--sand","value":"#E8E3D7","kind":"color","definedIn":"tokens/colors.css"},{"name":"--ink-900","value":"#14171C","kind":"color","definedIn":"tokens/colors.css"},{"name":"--ink-800","value":"#232932","kind":"color","definedIn":"tokens/colors.css"},{"name":"--ink-700","value":"#3A424E","kind":"color","definedIn":"tokens/colors.css"},{"name":"--ink-600","value":"#545E6C","kind":"color","definedIn":"tokens/colors.css"},{"name":"--ink-500","value":"#707A87","kind":"color","definedIn":"tokens/colors.css"},{"name":"--ink-400","value":"#939BA6","kind":"color","definedIn":"tokens/colors.css"},{"name":"--ink-300","value":"#BCC2CA","kind":"color","definedIn":"tokens/colors.css"},{"name":"--ink-200","value":"#DCE0E5","kind":"color","definedIn":"tokens/colors.css"},{"name":"--ink-100","value":"#ECEEF1","kind":"color","definedIn":"tokens/colors.css"},{"name":"--white","value":"#FFFFFF","kind":"color","definedIn":"tokens/colors.css"},{"name":"--success-600","value":"#2E7D54","kind":"color","definedIn":"tokens/colors.css"},{"name":"--success-100","value":"#E0F0E7","kind":"color","definedIn":"tokens/colors.css"},{"name":"--warning-600","value":"#B5811E","kind":"color","definedIn":"tokens/colors.css"},{"name":"--warning-100","value":"#F8EBCF","kind":"color","definedIn":"tokens/colors.css"},{"name":"--danger-600","value":"#B23B36","kind":"color","definedIn":"tokens/colors.css"},{"name":"--danger-100","value":"#F6E2E0","kind":"color","definedIn":"tokens/colors.css"},{"name":"--info-600","value":"#1E4670","kind":"color","definedIn":"tokens/colors.css"},{"name":"--info-100","value":"#E2EBF3","kind":"color","definedIn":"tokens/colors.css"},{"name":"--color-brand","value":"var(--navy-800)","kind":"color","definedIn":"tokens/colors.css"},{"name":"--color-brand-strong","value":"var(--navy-900)","kind":"color","definedIn":"tokens/colors.css"},{"name":"--color-accent","value":"var(--gold-600)","kind":"color","definedIn":"tokens/colors.css"},{"name":"--color-accent-strong","value":"var(--gold-700)","kind":"color","definedIn":"tokens/colors.css"},{"name":"--surface-page","value":"var(--ivory)","kind":"color","definedIn":"tokens/colors.css"},{"name":"--surface-card","value":"var(--white)","kind":"color","definedIn":"tokens/colors.css"},{"name":"--surface-raised","value":"var(--paper)","kind":"color","definedIn":"tokens/colors.css"},{"name":"--surface-sunken","value":"var(--paper-2)","kind":"color","definedIn":"tokens/colors.css"},{"name":"--surface-inverse","value":"var(--navy-800)","kind":"color","definedIn":"tokens/colors.css"},{"name":"--surface-accent-soft","value":"var(--gold-50)","kind":"color","definedIn":"tokens/colors.css"},{"name":"--surface-brand-soft","value":"var(--navy-50)","kind":"color","definedIn":"tokens/colors.css"},{"name":"--text-strong","value":"var(--ink-900)","kind":"font","definedIn":"tokens/colors.css"},{"name":"--text-body","value":"var(--ink-800)","kind":"font","definedIn":"tokens/colors.css"},{"name":"--text-muted","value":"var(--ink-500)","kind":"font","definedIn":"tokens/colors.css"},{"name":"--text-subtle","value":"var(--ink-400)","kind":"font","definedIn":"tokens/colors.css"},{"name":"--text-on-brand","value":"var(--ivory)","kind":"font","definedIn":"tokens/colors.css"},{"name":"--text-on-accent","value":"var(--navy-900)","kind":"font","definedIn":"tokens/colors.css"},{"name":"--text-accent","value":"var(--gold-700)","kind":"font","definedIn":"tokens/colors.css"},{"name":"--text-link","value":"var(--navy-600)","kind":"font","definedIn":"tokens/colors.css"},{"name":"--border-subtle","value":"var(--ink-200)","kind":"color","definedIn":"tokens/colors.css"},{"name":"--border-default","value":"var(--ink-300)","kind":"color","definedIn":"tokens/colors.css"},{"name":"--border-strong","value":"var(--ink-400)","kind":"color","definedIn":"tokens/colors.css"},{"name":"--border-accent","value":"var(--gold-600)","kind":"color","definedIn":"tokens/colors.css"},{"name":"--border-brand","value":"var(--navy-800)","kind":"color","definedIn":"tokens/colors.css"},{"name":"--focus-ring","value":"var(--gold-600)","kind":"color","definedIn":"tokens/colors.css"},{"name":"--font-sans","value":"'IBM Plex Sans Arabic', 'Segoe UI', Tahoma, system-ui, sans-serif","kind":"font","definedIn":"tokens/typography.css"},{"name":"--font-mono","value":"'IBM Plex Mono', 'SF Mono', ui-monospace, monospace","kind":"font","definedIn":"tokens/typography.css"},{"name":"--font-display","value":"var(--font-sans)","kind":"font","definedIn":"tokens/typography.css"},{"name":"--fw-light","value":"300","kind":"font","definedIn":"tokens/typography.css","annotation":"font"},{"name":"--fw-regular","value":"400","kind":"font","definedIn":"tokens/typography.css","annotation":"font"},{"name":"--fw-medium","value":"500","kind":"font","definedIn":"tokens/typography.css","annotation":"font"},{"name":"--fw-semibold","value":"600","kind":"font","definedIn":"tokens/typography.css","annotation":"font"},{"name":"--fw-bold","value":"700","kind":"font","definedIn":"tokens/typography.css","annotation":"font"},{"name":"--fs-display","value":"56px","kind":"spacing","definedIn":"tokens/typography.css"},{"name":"--fs-h1","value":"40px","kind":"spacing","definedIn":"tokens/typography.css"},{"name":"--fs-h2","value":"32px","kind":"spacing","definedIn":"tokens/typography.css"},{"name":"--fs-h3","value":"25px","kind":"spacing","definedIn":"tokens/typography.css"},{"name":"--fs-h4","value":"20px","kind":"spacing","definedIn":"tokens/typography.css"},{"name":"--fs-lg","value":"18px","kind":"spacing","definedIn":"tokens/typography.css"},{"name":"--fs-body","value":"16px","kind":"spacing","definedIn":"tokens/typography.css"},{"name":"--fs-sm","value":"14px","kind":"spacing","definedIn":"tokens/typography.css"},{"name":"--fs-xs","value":"13px","kind":"spacing","definedIn":"tokens/typography.css"},{"name":"--fs-2xs","value":"11px","kind":"spacing","definedIn":"tokens/typography.css"},{"name":"--lh-tight","value":"1.2","kind":"other","definedIn":"tokens/typography.css","annotation":"other"},{"name":"--lh-snug","value":"1.35","kind":"other","definedIn":"tokens/typography.css","annotation":"other"},{"name":"--lh-normal","value":"1.6","kind":"other","definedIn":"tokens/typography.css","annotation":"other"},{"name":"--lh-relaxed","value":"1.8","kind":"other","definedIn":"tokens/typography.css","annotation":"other"},{"name":"--ls-tight","value":"-0.01em","kind":"other","definedIn":"tokens/typography.css","annotation":"other"},{"name":"--ls-normal","value":"0","kind":"other","definedIn":"tokens/typography.css","annotation":"other"},{"name":"--ls-wide","value":"0.04em","kind":"other","definedIn":"tokens/typography.css","annotation":"other"},{"name":"--ls-caps","value":"0.08em","kind":"other","definedIn":"tokens/typography.css","annotation":"other"},{"name":"--text-display-size","value":"var(--fs-display)","kind":"font","definedIn":"tokens/typography.css"},{"name":"--text-display-weight","value":"var(--fw-bold)","kind":"font","definedIn":"tokens/typography.css","annotation":"font"},{"name":"--text-display-lh","value":"var(--lh-tight)","kind":"other","definedIn":"tokens/typography.css","annotation":"other"},{"name":"--text-heading-weight","value":"var(--fw-semibold)","kind":"font","definedIn":"tokens/typography.css","annotation":"font"},{"name":"--text-heading-lh","value":"var(--lh-snug)","kind":"other","definedIn":"tokens/typography.css","annotation":"other"},{"name":"--text-body-size","value":"var(--fs-body)","kind":"font","definedIn":"tokens/typography.css"},{"name":"--text-body-weight","value":"var(--fw-regular)","kind":"font","definedIn":"tokens/typography.css","annotation":"font"},{"name":"--text-body-lh","value":"var(--lh-normal)","kind":"other","definedIn":"tokens/typography.css","annotation":"other"},{"name":"--text-label-weight","value":"var(--fw-medium)","kind":"font","definedIn":"tokens/typography.css","annotation":"font"},{"name":"--text-eyebrow-spacing","value":"var(--ls-caps)","kind":"other","definedIn":"tokens/typography.css","annotation":"other"},{"name":"--space-0","value":"0","kind":"spacing","definedIn":"tokens/spacing.css"},{"name":"--space-1","value":"4px","kind":"spacing","definedIn":"tokens/spacing.css"},{"name":"--space-2","value":"8px","kind":"spacing","definedIn":"tokens/spacing.css"},{"name":"--space-3","value":"12px","kind":"spacing","definedIn":"tokens/spacing.css"},{"name":"--space-4","value":"16px","kind":"spacing","definedIn":"tokens/spacing.css"},{"name":"--space-5","value":"20px","kind":"spacing","definedIn":"tokens/spacing.css"},{"name":"--space-6","value":"24px","kind":"spacing","definedIn":"tokens/spacing.css"},{"name":"--space-7","value":"32px","kind":"spacing","definedIn":"tokens/spacing.css"},{"name":"--space-8","value":"40px","kind":"spacing","definedIn":"tokens/spacing.css"},{"name":"--space-9","value":"48px","kind":"spacing","definedIn":"tokens/spacing.css"},{"name":"--space-10","value":"64px","kind":"spacing","definedIn":"tokens/spacing.css"},{"name":"--space-11","value":"80px","kind":"spacing","definedIn":"tokens/spacing.css"},{"name":"--space-12","value":"96px","kind":"spacing","definedIn":"tokens/spacing.css"},{"name":"--space-13","value":"128px","kind":"spacing","definedIn":"tokens/spacing.css"},{"name":"--gap-inline","value":"var(--space-2)","kind":"spacing","definedIn":"tokens/spacing.css"},{"name":"--gap-stack","value":"var(--space-4)","kind":"spacing","definedIn":"tokens/spacing.css"},{"name":"--pad-card","value":"var(--space-6)","kind":"spacing","definedIn":"tokens/spacing.css"},{"name":"--pad-section","value":"var(--space-10)","kind":"spacing","definedIn":"tokens/spacing.css"},{"name":"--container-max","value":"1200px","kind":"spacing","definedIn":"tokens/spacing.css"},{"name":"--content-max","value":"720px","kind":"spacing","definedIn":"tokens/spacing.css"},{"name":"--radius-none","value":"0","kind":"radius","definedIn":"tokens/radius.css"},{"name":"--radius-xs","value":"3px","kind":"radius","definedIn":"tokens/radius.css"},{"name":"--radius-sm","value":"5px","kind":"radius","definedIn":"tokens/radius.css"},{"name":"--radius-md","value":"8px","kind":"radius","definedIn":"tokens/radius.css"},{"name":"--radius-lg","value":"12px","kind":"radius","definedIn":"tokens/radius.css"},{"name":"--radius-xl","value":"16px","kind":"radius","definedIn":"tokens/radius.css"},{"name":"--radius-2xl","value":"22px","kind":"radius","definedIn":"tokens/radius.css"},{"name":"--radius-pill","value":"999px","kind":"radius","definedIn":"tokens/radius.css"},{"name":"--radius-button","value":"var(--radius-md)","kind":"radius","definedIn":"tokens/radius.css"},{"name":"--radius-card","value":"var(--radius-lg)","kind":"radius","definedIn":"tokens/radius.css"},{"name":"--radius-input","value":"var(--radius-md)","kind":"radius","definedIn":"tokens/radius.css"},{"name":"--shadow-xs","value":"0 1px 2px rgba(15, 42, 74, 0.06)","kind":"shadow","definedIn":"tokens/shadows.css"},{"name":"--shadow-sm","value":"0 1px 3px rgba(15, 42, 74, 0.08), 0 1px 2px rgba(15, 42, 74, 0.04)","kind":"shadow","definedIn":"tokens/shadows.css"},{"name":"--shadow-md","value":"0 4px 12px rgba(15, 42, 74, 0.08), 0 2px 4px rgba(15, 42, 74, 0.05)","kind":"shadow","definedIn":"tokens/shadows.css"},{"name":"--shadow-lg","value":"0 12px 28px rgba(15, 42, 74, 0.12), 0 4px 10px rgba(15, 42, 74, 0.06)","kind":"shadow","definedIn":"tokens/shadows.css"},{"name":"--shadow-xl","value":"0 24px 52px rgba(15, 42, 74, 0.16), 0 8px 18px rgba(15, 42, 74, 0.08)","kind":"shadow","definedIn":"tokens/shadows.css"},{"name":"--shadow-focus","value":"0 0 0 3px rgba(184, 146, 76, 0.35)","kind":"shadow","definedIn":"tokens/shadows.css"},{"name":"--shadow-inset","value":"inset 0 1px 2px rgba(15, 42, 74, 0.05)","kind":"shadow","definedIn":"tokens/shadows.css"},{"name":"--hairline","value":"1px solid var(--border-subtle)","kind":"color","definedIn":"tokens/shadows.css"},{"name":"--ease-standard","value":"cubic-bezier(0.4, 0.0, 0.2, 1)","kind":"other","definedIn":"tokens/motion.css","annotation":"other"},{"name":"--ease-out","value":"cubic-bezier(0.0, 0.0, 0.2, 1)","kind":"other","definedIn":"tokens/motion.css","annotation":"other"},{"name":"--ease-in","value":"cubic-bezier(0.4, 0.0, 1, 1)","kind":"other","definedIn":"tokens/motion.css","annotation":"other"},{"name":"--dur-fast","value":"120ms","kind":"other","definedIn":"tokens/motion.css","annotation":"other"},{"name":"--dur-base","value":"200ms","kind":"other","definedIn":"tokens/motion.css","annotation":"other"},{"name":"--dur-slow","value":"320ms","kind":"other","definedIn":"tokens/motion.css","annotation":"other"},{"name":"--transition-base","value":"all var(--dur-base) var(--ease-standard)","kind":"color","definedIn":"tokens/motion.css"},{"name":"--transition-color","value":"color var(--dur-fast) var(--ease-standard),\n                      background-color var(--dur-fast) var(--ease-standard),\n                      border-color var(--dur-fast) var(--ease-standard)","kind":"color","definedIn":"tokens/motion.css"}],"themes":[],"fonts":[{"family":"IBM Plex Sans Arabic","weight":"300","style":"normal","cssPath":"tokens/fonts.css","files":[],"remoteSrc":true},{"family":"IBM Plex Sans Arabic","weight":"400","style":"normal","cssPath":"tokens/fonts.css","files":[],"remoteSrc":true},{"family":"IBM Plex Sans Arabic","weight":"500","style":"normal","cssPath":"tokens/fonts.css","files":[],"remoteSrc":true},{"family":"IBM Plex Sans Arabic","weight":"600","style":"normal","cssPath":"tokens/fonts.css","files":[],"remoteSrc":true},{"family":"IBM Plex Sans Arabic","weight":"700","style":"normal","cssPath":"tokens/fonts.css","files":[],"remoteSrc":true},{"family":"IBM Plex Mono","weight":"400","style":"normal","cssPath":"tokens/fonts.css","files":[],"remoteSrc":true},{"family":"IBM Plex Mono","weight":"500","style":"normal","cssPath":"tokens/fonts.css","files":[],"remoteSrc":true},{"family":"IBM Plex Mono","weight":"600","style":"normal","cssPath":"tokens/fonts.css","files":[],"remoteSrc":true}],"brandFonts":[{"family":"IBM Plex Sans Arabic","status":"ok","tokens":["--font-sans"],"path":"tokens/fonts.css"},{"family":"IBM Plex Mono","status":"ok","tokens":["--font-mono"],"path":"tokens/fonts.css"}],"source":"spa"}